gaudi/__init__.py
gaudi/domain_model.py
gaudi/response_object.py
gaudi/use_case.py
gaudi-1.0.1.dist-info/DESCRIPTION.rst
gaudi-1.0.1.dist-info/METADATA
gaudi-1.0.1.dist-info/RECORD
gaudi-1.0.1.dist-info/WHEEL
gaudi-1.0.1.dist-info/metadata.json
gaudi-1.0.1.dist-info/top_level.txt
