Metadata-Version: 2.0
Name: gaudi
Version: 1.0.1
Summary: A helper library for Clean Architectures in Python
Home-page: https://github.com/lgiordani/gaudi
Author: Leonardo Giordani
Author-email: giordani.leonardo@gmail.com
License: MIT license
Keywords: gaudi
Platform: UNKNOWN
Classifier: Development Status :: 5 - Production/Stable
Classifier: Intended Audience :: Developers
Classifier: License :: OSI Approved :: MIT License
Classifier: Natural Language :: English
Classifier: Programming Language :: Python :: 3
